notesecret/__init__.py
notesecret/base.py
notesecret/fernet.py
notesecret/secret.py
notesecret-0.0.13.dist-info/METADATA
notesecret-0.0.13.dist-info/WHEEL
notesecret-0.0.13.dist-info/top_level.txt
notesecret-0.0.13.dist-info/RECORD
